telegram_download_daemon_ng/__init__.py
telegram_download_daemon_ng/__main__.py
telegram_download_daemon_ng/cli.py
telegram_download_daemon_ng/config.py
telegram_download_daemon_ng/constants.py
telegram_download_daemon_ng/download_media.py
telegram_download_daemon_ng/session_manager.py
telegram_download_daemon_ng/utils.py
telegram_download_daemon_ng-1.0.0b9.dist-info/WHEEL
telegram_download_daemon_ng-1.0.0b9.dist-info/entry_points.txt
telegram_download_daemon_ng-1.0.0b9.dist-info/METADATA
telegram_download_daemon_ng-1.0.0b9.dist-info/RECORD
