Metadata-Version: 2.4
Name: telegram-download-daemon-ng
Version: 1.0.0b9
Summary: A daemon to automate telegram download of big files.
Keywords: download,downloads,telegram
Author: Luis Zurro
Author-email: Luis Zurro <luiszurrodecos@gmail.com>
License-Expression: GPL-3.0-or-later
Classifier: Development Status :: 3 - Alpha
Classifier: Intended Audience :: System Administrators
Classifier: Natural Language :: English
Classifier: Operating System :: OS Independent
Classifier: Programming Language :: Python :: 3.9
Classifier: Programming Language :: Python :: 3.10
Classifier: Programming Language :: Python :: 3.11
Classifier: Programming Language :: Python :: 3.12
Classifier: Programming Language :: Python :: 3.13
Requires-Dist: cffi==2.0.0
Requires-Dist: cryptg==0.5.1
Requires-Dist: pyaes==1.6.1
Requires-Dist: pyasn1==0.6.1
Requires-Dist: pycparser==2.23
Requires-Dist: rsa==4.9.1
Requires-Dist: telethon==1.41.2
Requires-Dist: humanize==4.13.0
Requires-Python: >=3.9, <4.0
Project-URL: Homepage, https://github.com/Nyaran/telegram-download-daemon-ng
Project-URL: Sponsor, https://github.com/sponsors/Nyaran
Project-URL: Tracker, https://github.com/Nyaran/telegram-download-daemon-ng/issues
